widgy_blog/site.py
widgy_blog/sitemaps.py
widgy_blog/search_indexes.py
widgy_blog/utils.py
widgy_blog/urls.py
widgy_blog/__init__.py
widgy_blog/admin.py
widgy_blog/models.py
widgy_blog/views.py
widgy_blog/migrations/0001_initial.py
widgy_blog/migrations/0002_auto_20150617_1302.py
widgy_blog/migrations/0003_auto_20150701_1432.py
widgy_blog/migrations/0004_auto_20150710_1604.py
widgy_blog/migrations/0005_auto_20150722_1048.py
widgy_blog/migrations/__init__.py
widgy_blog/south_migrations/0001_initial.py
widgy_blog/south_migrations/0002_auto__add_field_bloglayout_description__add_field_bloglayout_keywords_.py
widgy_blog/south_migrations/0003_auto__chg_field_bloglayout_date.py
widgy_blog/south_migrations/__init__.py
widgy_blog/templates/widgy/widgy_blog/archive_list.html
widgy_blog/templates/widgy/widgy_blog/blog_detail.html
widgy_blog/templates/widgy/widgy_blog/blog_list.html
widgy_blog/templates/widgy/widgy_blog/pagination.html
django_widgy_blog-0.2.0.dist-info/top_level.txt
django_widgy_blog-0.2.0.dist-info/METADATA
django_widgy_blog-0.2.0.dist-info/DESCRIPTION.rst
django_widgy_blog-0.2.0.dist-info/metadata.json
django_widgy_blog-0.2.0.dist-info/WHEEL
django_widgy_blog-0.2.0.dist-info/RECORD
