Metadata-Version: 2.0
Name: django-widgy-blog
Version: 0.2.0
Summary: Reusable blog app for Django-Widgy
Home-page: https://github.com/fusionbox/django-widgy-blog/
Author: Fusionbox, Inc.
Author-email: programmers@fusionbox.com
License: BSD
Platform: UNKNOWN
Classifier: Environment :: Web Environment
Classifier: Framework :: Django
Classifier: Intended Audience :: Developers
Classifier: License :: OSI Approved :: BSD License
Classifier: Natural Language :: English
Classifier: Programming Language :: Python
Classifier: Programming Language :: Python :: 2.7
Classifier: Programming Language :: Python :: 3
Requires-Dist: django-widgy
